cubicweb_notebooks/__init__.py
cubicweb_notebooks/__pkginfo__.py
cubicweb_notebooks/entities.py
cubicweb_notebooks/hooks.py
cubicweb_notebooks/schema.py
cubicweb_notebooks/views.py
cubicweb_notebooks/workflow.py
cubicweb_notebooks/data/lab/bootstrap.js
cubicweb_notebooks/data/lab/config-utils.js
cubicweb_notebooks/data/lab/icon-120x120.png
cubicweb_notebooks/data/lab/icon-512x512.png
cubicweb_notebooks/data/lab/index.html
cubicweb_notebooks/data/lab/jupyter-lite.ipynb
cubicweb_notebooks/data/lab/jupyter-lite.json
cubicweb_notebooks/data/lab/jupyterlite.schema.v0.json
cubicweb_notebooks/data/lab/manifest.webmanifest
cubicweb_notebooks/data/lab/package.json
cubicweb_notebooks/data/lab/service-worker.js
cubicweb_notebooks/data/lab/api/translations/all.json
cubicweb_notebooks/data/lab/api/translations/en.json
cubicweb_notebooks/data/lab/build/1053.7a56130.js
cubicweb_notebooks/data/lab/build/1053.7a56130.js.map
cubicweb_notebooks/data/lab/build/1088.33c6076.js
cubicweb_notebooks/data/lab/build/1088.33c6076.js.map
cubicweb_notebooks/data/lab/build/1091.1cf35e6.js
cubicweb_notebooks/data/lab/build/1091.1cf35e6.js.map
cubicweb_notebooks/data/lab/build/1122.d86c258.js
cubicweb_notebooks/data/lab/build/1122.d86c258.js.map
cubicweb_notebooks/data/lab/build/114.1c04540.js
cubicweb_notebooks/data/lab/build/114.1c04540.js.map
cubicweb_notebooks/data/lab/build/125.0c9600e.js
cubicweb_notebooks/data/lab/build/125.0c9600e.js.map
cubicweb_notebooks/data/lab/build/1385.1a02d9b.js
cubicweb_notebooks/data/lab/build/1385.1a02d9b.js.map
cubicweb_notebooks/data/lab/build/1418.d9431d8.js
cubicweb_notebooks/data/lab/build/1418.d9431d8.js.map
cubicweb_notebooks/data/lab/build/1542.22098a5.js
cubicweb_notebooks/data/lab/build/1542.22098a5.js.LICENSE.txt
cubicweb_notebooks/data/lab/build/1542.22098a5.js.map
cubicweb_notebooks/data/lab/build/1558.548303d.js
cubicweb_notebooks/data/lab/build/1558.548303d.js.map
cubicweb_notebooks/data/lab/build/1584.d919fce.js
cubicweb_notebooks-0.1.0.dist-info/METADATA
cubicweb_notebooks-0.1.0.dist-info/WHEEL
cubicweb_notebooks-0.1.0.dist-info/entry_points.txt
cubicweb_notebooks-0.1.0.dist-info/top_level.txt
cubicweb_notebooks-0.1.0.dist-info/RECORD
