Metadata-Version: 2.1
Name: cubicweb-notebooks
Version: 0.1.0
Summary: A cube to deal with Jupyter-notebooks and voici view
Home-page: https://forge.extranet.logilab.fr/cubicweb/cubes/notebooks
Author: LOGILAB S.A. (Paris, FRANCE)
Author-email: contact@logilab.fr
License: LGPL
Classifier: Environment :: Web Environment
Classifier: Framework :: CubicWeb
Classifier: Programming Language :: Python :: 3
Classifier: Programming Language :: JavaScript
Requires-Dist: cubicweb >=4.2.0
Requires-Dist: cubicweb-web >=1.2.9
